{
  "typingHistory": [
    {
      "wpm": 7,
      "accuracy": 2.735562310030395,
      "duration": 15,
      "createdAt": "2025-02-27T21:44:25.372Z"
    },
    {
      "wpm": 38,
      "accuracy": 80,
      "duration": 15,
      "createdAt": "2025-02-27T22:01:24.470Z"
    },
    {
      "wpm": 50,
      "accuracy": 90.41095890410958,
      "duration": 15,
      "createdAt": "2025-02-27T22:02:13.471Z"
    },
    {
      "wpm": 50,
      "accuracy": 90.41095890410958,
      "duration": 15,
      "createdAt": "2025-02-27T22:02:13.471Z"
    },
    {
      "wpm": 50,
      "accuracy": 90.41095890410958,
      "duration": 15,
      "createdAt": "2025-02-27T22:02:13.471Z"
    },
    {
      "wpm": 50,
      "accuracy": 90.41095890410958,
      "duration": 15,
      "createdAt": "2025-02-27T22:02:13.471Z"
    },
    {
      "wpm": 50,
      "accuracy": 90.41095890410958,
      "duration": 15,
      "createdAt": "2025-02-27T22:02:13.471Z"
    },
    {
      "wpm": 50,
      "accuracy": 90.41095890410958,
      "duration": 15,
      "createdAt": "2025-02-27T22:02:13.471Z"
    },
    {
      "wpm": 50,
      "accuracy": 90.41095890410958,
      "duration": 15,
      "createdAt": "2025-02-27T22:02:13.471Z"
    },
    {
      "wpm": 50,
      "accuracy": 90.41095890410958,
      "duration": 15,
      "createdAt": "2025-02-27T22:02:13.471Z"
    }
  ],
  "success": true
}
